phonex/__init__.py
phonex-0.0.2.dist-info/METADATA
phonex-0.0.2.dist-info/WHEEL
phonex-0.0.2.dist-info/top_level.txt
phonex-0.0.2.dist-info/RECORD
