Metadata-Version: 2.1
Name: phonex
Version: 0.0.2
Summary: Phonex algorithm for python3
Home-page: https://github.com/damiencorpataux/phonex
Author: Damien Corpataux
Author-email: d@mien.ch
License: MIT
Platform: UNKNOWN
